pyvfg/__init__.py
pyvfg/api.py
pyvfg/errors/__init__.py
pyvfg/errors/base.py
pyvfg/errors/bayes_net.py
pyvfg/errors/factor_graph.py
pyvfg/errors/mrf.py
pyvfg/errors/pomdp.py
pyvfg/project/README.md
pyvfg/project/__init__.py
pyvfg/project/model.py
pyvfg/project/serialization.py
pyvfg/project/serialization_backwards_compat.py
pyvfg/project/utils.py
pyvfg/py.typed
pyvfg/pydantic_types.py
pyvfg/versions/__init__.py
pyvfg/versions/common.py
pyvfg/versions/v_0_2_0/__init__.py
pyvfg/versions/v_0_2_0/vfg_0_2_0.py
pyvfg/versions/v_0_5_0/README.md
pyvfg/versions/v_0_5_0/__init__.py
pyvfg/versions/v_0_5_0/bayesian_network.py
pyvfg/versions/v_0_5_0/markov_random_field.py
pyvfg/versions/v_0_5_0/pomdp.py
pyvfg/versions/v_0_5_0/vfg_0_5_0.py
pyvfg/versions/v_0_5_0/vfg_0_5_0_utils.py
pyvfg/versions/v_2_0_0/__init__.py
pyvfg/versions/v_2_0_0/vfg_2_0_0_schema.json
pyvfg/versions/v_2_0_1/__init__.py
pyvfg/versions/v_2_0_1/factor.py
pyvfg/versions/v_2_0_1/variable.py
pyvfg/versions/v_2_0_1/vfg_2_0_1.py
pyvfg/versions/v_2_0_1/vfg_2_0_1_schema.json
pyvfg/versions/v_2_0_1/vfg_2_0_1_utils.py
pyvfg/versions/v_2_1_0/__init__.py
pyvfg/versions/v_2_1_0/vfg_2_1_0_schema.json
pyvfg/versions/v_2_1_1/__init__.py
pyvfg/versions/v_2_1_1/vfg_2_1_1.py
pyvfg/versions/v_2_1_1/vfg_2_1_1_schema.json
pyvfg/versions/v_2_1_1/vfg_2_1_1_utils.py
pyvfg-8.2.2.dist-info/WHEEL
pyvfg-8.2.2.dist-info/METADATA
pyvfg-8.2.2.dist-info/RECORD
