Metadata-Version: 2.3
Name: pyvfg
Version: 8.2.2
Summary: 
Author: VERSES, Jasmine Moore, Alex Kiefer, Alessandro Muzzi
Author-email: VERSES <info@verses.ai>, Jasmine Moore <jasmine.moore@verses.ai>, Alex Kiefer <alex.kiefer@verses.ai>, Alessandro Muzzi <alessandro.muzzi@verses.ai>
Requires-Dist: uv-build
Requires-Dist: pydantic>=2.8.2
Requires-Dist: dataclass-wizard>=0.35.1
Requires-Dist: jsonpatch>=1.33
Requires-Dist: networkx~=3.4.2
Requires-Dist: scipy~=1.14.1
Requires-Dist: numpy>=1.26.4,<2.3.0
Requires-Dist: deprecation~=2.1.0
Requires-Dist: pathlib>=1.0.1
Requires-Python: >=3.11
